README.rst
setup.py
slict/__init__.py
slict/core.py
slict.egg-info/PKG-INFO
slict.egg-info/SOURCES.txt
slict.egg-info/dependency_links.txt
slict.egg-info/top_level.txt
slict.egg-info/zip-safe