Metadata-Version: 1.0
Name: slict
Version: 0.2.3
Summary: Sliceable dictionary
Home-page: http://github.com/maxhutch/slict/
Author: Max Hutchinson
Author-email: maxhutch@gmail.com
License: BSD
Keywords: dictionary slice
Platform: UNKNOWN
